tko/__init__.py
tko/__main__.py
tko/cmds/__init__.py
tko/cmds/cmd_build.py
tko/cmds/cmd_config.py
tko/cmds/cmd_diff.py
tko/cmds/cmd_down.py
tko/cmds/cmd_eval.py
tko/cmds/cmd_open.py
tko/cmds/cmd_rep.py
tko/cmds/cmd_run.py
tko/cmds/cmd_task.py
tko/down/__init__.py
tko/down/drafts.py
tko/enums/__init__.py
tko/enums/diff_count.py
tko/enums/diff_mode.py
tko/enums/execution_result.py
tko/enums/identifier_type.py
tko/enums/success.py
tko/feno/__init__.py
tko/feno/build.py
tko/feno/cases.py
tko/feno/feno.py
tko/feno/filter.py
tko/feno/grading.py
tko/feno/html.py
tko/feno/indexer.py
tko/feno/jsontools.py
tko/feno/log.py
tko/feno/mdpp.py
tko/feno/older.py
tko/feno/remote_md.py
tko/feno/title.py
tko/game/__init__.py
tko/game/cluster.py
tko/game/game.py
tko/game/game_builder.py
tko/game/game_validator.py
tko/game/quest.py
tko/game/quest_grader.py
tko/game/quest_parser.py
tko/game/task.py
tko/game/task_grader.py
tko/game/task_info.py
tko/game/task_parser.py
tko/game/tree_item.py
tko/logger/__init__.py
tko/logger/delta.py
tko/logger/kv.py
tko/logger/log_history.py
tko/logger/log_item_base.py
tko/logger/log_item_exec.py
tko/logger/log_item_move.py
tko/logger/log_item_self.py
tko/logger/log_sort.py
tko/logger/logger.py
tko/logger/old_log_loader.py
tko/logger/task_resume.py
tko/mico/__init__.py
tko/mico/class_task.py
tko/mico/collect.py
tko/mico/collected.py
tko/mico/csv_tools.py
tko/mico/join.py
tko/mico/mico.py
tko/mico/pull.py
tko/mico/student_repo.py
tko/play/__init__.py
tko/play/border.py
tko/play/colors.py
tko/play/daily_graph.py
tko/play/flag_functors.py
tko/play/flags.py
tko/play/floating.py
tko/play/floating_calibrate.py
tko/play/floating_grade.py
tko/play/floating_manager.py
tko/play/fmt.py
tko/play/frame.py
tko/play/gui.py
tko/play/images.py
tko/play/input_manager.py
tko/play/keys.py
tko/play/language_setter.py
tko/play/opener.py
tko/play/patch_history.py
tko/play/play.py
tko/play/play_actions.py
tko/play/play_config.py
tko/play/search.py
tko/play/task_graph.py
tko-7.5.1.dist-info/METADATA
tko-7.5.1.dist-info/WHEEL
tko-7.5.1.dist-info/entry_points.txt
tko-7.5.1.dist-info/top_level.txt
tko-7.5.1.dist-info/RECORD
