Metadata-Version: 2.4
Name: tko
Version: 7.5.1
Summary: Add your description here
Author-email: David <sena.ufc@gmail.com>
License-Expression: MIT
Requires-Python: >=3.10
Requires-Dist: appdirs>=1.4.4
Requires-Dist: chardet>=5.2.0
Requires-Dist: diff-match-patch>=20241021
Requires-Dist: icecream>=2.1.4
Requires-Dist: markdown>=3.7
Requires-Dist: pip>=25.0.1
Requires-Dist: pygments>=2.19.1
Requires-Dist: pymdown-extensions>=10.15
Requires-Dist: pyyaml>=6.0.2
Requires-Dist: types-appdirs>=1.4.3.5
Requires-Dist: types-chardet>=5.0.4.6
Requires-Dist: types-markdown>=3.7.0.20250322
Requires-Dist: uniplot==0.17.1
Requires-Dist: windows-curses; platform_system == "Windows"
